{
	"authors": [
		"Hipreme"
	],
	"copyright": "Copyright © 2020, Hipreme",
	"dependencies": {
		"bindbc-opengl": "~>1.0.0",
		"bindbc-sdl": "~>0.19.2"
	},
	"description": "A minimal bindbc-cimgui example using sdl and opengl",
	"importPaths": [
		"source",
		"../source"
	],
	"libs": [
		"../lib/cimgui"
	],
	"license": "BSL-1.0",
	"name": "bindbc-cimgui_sample",
	"sourcePaths": [
		"source"
	],
	"lflags-windows": [
		"/LIBPATH:bin",
		"/NODEFAULTLIB:libcmt",
		"/NODEFAULTLIB:libvcruntime",
		"/NODEFAULTLIB:libucrt"
	],
	"targetPath": "bin",
	"versions": [
		"CIMGUI_VIEWPORT_BRANCH",
		"SDL_208",
		"BindSDL_TTF",
		"BindSDL_Image",
		"GL_33",
		"GL_ARB"
	]
}